pcore/__init__.py
pcore/__main__.py
pcore/commands/__init__.py
pcore/commands/clusters/__init__.py
pcore/commands/clusters/cluster_manager.py
pcore/commands/clusters/enums.py
pcore/commands/clusters/gcp/__init__.py
pcore/commands/clusters/gcp/configurations/__init__.py
pcore/commands/clusters/gcp/configurations/compute_resource.py
pcore/commands/clusters/gcp/configurations/event_monitor.py
pcore/commands/clusters/gcp/configurations/main_api.py
pcore/commands/clusters/gcp/configurations/postgres.py
pcore/commands/clusters/gcp/configurations/redis.py
pcore/commands/clusters/gcp/configurations/secrets.py
pcore/commands/clusters/gcp/gpu.py
pcore/commands/clusters/gcp/manager.py
pcore/commands/clusters/parser.py
pcore/commands/clusters/pcloud/__init__.py
pcore/commands/clusters/pcloud/configurations/__init__.py
pcore/commands/clusters/pcloud/configurations/compute_resource.py
pcore/commands/clusters/pcloud/configurations/event_monitor.py
pcore/commands/clusters/pcloud/configurations/main_api.py
pcore/commands/clusters/pcloud/configurations/postgres.py
pcore/commands/clusters/pcloud/configurations/redis.py
pcore/commands/clusters/pcloud/configurations/secrets.py
pcore/commands/clusters/pcloud/manager.py
pcore/commands/credentials/__init__.py
pcore/commands/credentials/gcp.py
pcore/commands/credentials/parser.py
pcore/util/__init__.py
pcore/util/logging.py
pcore/util/progress_log.py
pipeline_core-0.0.0.dist-info/METADATA
pipeline_core-0.0.0.dist-info/WHEEL
pipeline_core-0.0.0.dist-info/entry_points.txt
pipeline_core-0.0.0.dist-info/RECORD
